cep_fetch/__init__.py
cep_fetch/cep_fetch.py
cep_fetch/py.typed
cep_fetch/core/domain.py
cep_fetch/core/interfaces.py
cep_fetch/providers/__init__.py
cep_fetch/providers/apicep.py
cep_fetch/providers/brasilapi.py
cep_fetch/providers/opencep.py
cep_fetch/providers/viacep.py
cep_fetch-0.1.3.dist-info/METADATA
cep_fetch-0.1.3.dist-info/WHEEL
cep_fetch-0.1.3.dist-info/licenses/LICENSE
cep_fetch-0.1.3.dist-info/RECORD
