Metadata-Version: 2.4
Name: cep-fetch
Version: 0.1.3
Summary: Fetch CEP information from multiple providers concurrently
Project-URL: Homepage, https://github.com/tiagoguatierri/cep-fetch
Project-URL: Documentation, https://github.com/tiagoguatierri/cep-fetch/README.md
Project-URL: Repository, https://github.com/tiagoguatierri/cep-fetch
Project-URL: Issues, https://github.com/tiagoguatierri/cep-fetch/issues
Project-URL: Changelog, https://github.com/tiagoguatierri/cep-fetch/changelog.md
Author-email: Tiago Guatieri <tiagovit@gmail.com>
License-Expression: MIT
License-File: LICENSE
Keywords: async,brazil,cep,concurrent,postal-code,zipcode
Classifier: Development Status :: 4 - Beta
Classifier: Framework :: AsyncIO
Classifier: Intended Audience :: Developers
Classifier: License :: OSI Approved :: MIT License
Classifier: Programming Language :: Python :: 3
Classifier: Programming Language :: Python :: 3.11
Classifier: Programming Language :: Python :: 3.12
Classifier: Programming Language :: Python :: 3.13
Classifier: Topic :: Software Development :: Libraries :: Python Modules
Classifier: Typing :: Typed
Requires-Python: >=3.11
Requires-Dist: aiohttp[speedups]>=3.13.2
